aioamqp_consumer_best/__init__.py
aioamqp_consumer_best/_connect.py
aioamqp_consumer_best/_helpers.py
aioamqp_consumer_best/_load_balancing_policy.py
aioamqp_consumer_best/base_middlewares.py
aioamqp_consumer_best/consumer.py
aioamqp_consumer_best/declare_queue.py
aioamqp_consumer_best/message.py
aioamqp_consumer_best/middlewares.py
aioamqp_consumer_best/py.typed
aioamqp_consumer_best/records.py
aioamqp_consumer_best-2.4.0.dist-info/LICENSE
aioamqp_consumer_best-2.4.0.dist-info/METADATA
aioamqp_consumer_best-2.4.0.dist-info/WHEEL
aioamqp_consumer_best-2.4.0.dist-info/top_level.txt
aioamqp_consumer_best-2.4.0.dist-info/RECORD
