Metadata-Version: 2.1
Name: aioamqp-consumer-best
Version: 2.4.0
Summary: Consumer utility for AMQP
Home-page: https://github.com/tkukushkin/aioamqp-consumer-best
Author: Timofey Kukushkin
Author-email: tima@kukushkin.me
License: MIT
Project-URL: Source, https://github.com/tkukushkin/aioamqp-consumer-best
Classifier: Development Status :: 4 - Beta
Classifier: Framework :: AsyncIO
Classifier: Intended Audience :: Developers
Classifier: License :: OSI Approved :: MIT License
Classifier: Operating System :: OS Independent
Classifier: Programming Language :: Python
Classifier: Programming Language :: Python :: 3
Classifier: Programming Language :: Python :: 3.10
Classifier: Programming Language :: Python :: 3.11
Classifier: Programming Language :: Python :: 3.12
Classifier: Topic :: Software Development :: Libraries :: Python Modules
Classifier: Typing :: Typed
Requires-Python: >=3.10
License-File: LICENSE
Requires-Dist: aioamqp
Requires-Dist: anyio >=4
Requires-Dist: exceptiongroup >=1.1.3
